ssb_dash_components/Accordion.py
ssb_dash_components/Button.py
ssb_dash_components/Checkbox.py
ssb_dash_components/Dialog.py
ssb_dash_components/Dropdown.py
ssb_dash_components/DropdownMultiple.py
ssb_dash_components/DropdownTest.py
ssb_dash_components/Example.py
ssb_dash_components/Glossary.py
ssb_dash_components/Header.py
ssb_dash_components/Input.py
ssb_dash_components/InputError.py
ssb_dash_components/Link.py
ssb_dash_components/Paragraph.py
ssb_dash_components/RequiredAsterisk.py
ssb_dash_components/Tabs.py
ssb_dash_components/Title.py
ssb_dash_components/__init__.py
ssb_dash_components/_imports_.py
ssb_dash_components/metadata.json
ssb_dash_components/package-info.json
ssb_dash_components/ssb_dash_components.min.js
ssb_dash_components/ssb_dash_components.min.js.map
ssb_dash_components-0.11.1.dist-info/METADATA
ssb_dash_components-0.11.1.dist-info/WHEEL
ssb_dash_components-0.11.1.dist-info/entry_points.txt
ssb_dash_components-0.11.1.dist-info/licenses/LICENSE
ssb_dash_components-0.11.1.dist-info/RECORD
