Metadata-Version: 2.4
Name: ssb-dash-components
Version: 0.11.1
Summary: Dash Component library for SSB
License: MIT
License-File: LICENSE
Author: Miles Mason Winther
Author-email: 42948872+mmwinther@users.noreply.github.com
Requires-Python: >=3.9,<4.0
Classifier: License :: OSI Approved :: MIT License
Classifier: Programming Language :: Python :: 3
Classifier: Programming Language :: Python :: 3.9
Classifier: Programming Language :: Python :: 3.10
Classifier: Programming Language :: Python :: 3.11
Classifier: Programming Language :: Python :: 3.12
Classifier: Programming Language :: Python :: 3.13
Classifier: Programming Language :: Python :: 3.14
Requires-Dist: dash (>=2.15.0)
